django_ffield/__init__.py
django_ffield/fields.py
django_ffield/utils.py
django_ffield/validators.py
django_ffield-0.0.6.dist-info/LICENSE
django_ffield-0.0.6.dist-info/METADATA
django_ffield-0.0.6.dist-info/WHEEL
django_ffield-0.0.6.dist-info/top_level.txt
django_ffield-0.0.6.dist-info/RECORD
