Metadata-Version: 2.1
Name: django-ffield
Version: 0.0.6
Summary: A Django Field with extra contol over fields
Author-email: Ali Sadeghi Far <booxgitboox@gmail.com>
Project-URL: Homepage, https://github.com/bigsbug/django-ffield
Project-URL: Bug Tracker, https://github.com/bigsbug/django-ffield/issues
Classifier: Programming Language :: Python :: 3
Classifier: License :: OSI Approved :: MIT License
Classifier: Operating System :: OS Independent
Classifier: Framework :: Django :: 3.0
Classifier: Framework :: Django :: 3.1
Classifier: Framework :: Django :: 3.2
Classifier: Framework :: Django :: 4
Classifier: Framework :: Django :: 4.1
Classifier: Framework :: Django :: 4.2
Classifier: Topic :: Utilities
Requires-Python: >=3.7
License-File: LICENSE
